[
  {"id": "rule_ashwagandha_pregnancy", "herb_id": "ashwagandha", "condition": "pregnancy", "severity": "high", "note": "Limited safety data in pregnancy; avoid unless cleared by a clinician."},
  {"id": "rule_ashwagandha_thyroid", "herb_id": "ashwagandha", "condition": "thyroid_disorder", "severity": "moderate", "note": "May influence thyroid hormone levels."},
  {"id": "rule_turmeric_anticoag", "herb_id": "turmeric", "condition": "anticoagulant_medication", "severity": "moderate", "note": "May increase bleeding risk when combined with blood thinners."},
  {"id": "rule_turmeric_gallstones", "herb_id": "turmeric", "condition": "gallstones", "severity": "moderate", "note": "May stimulate bile flow; caution with gallstones."},
  {"id": "rule_ginger_anticoag", "herb_id": "ginger", "condition": "anticoagulant_medication", "severity": "moderate", "note": "May increase bleeding risk when combined with blood thinners."},
  {"id": "rule_chamomile_sedative", "herb_id": "chamomile", "condition": "sedative_medication", "severity": "moderate", "note": "May compound drowsiness with sedative medications."},
  {"id": "rule_valerian_sedative", "herb_id": "valerian", "condition": "sedative_medication", "severity": "moderate", "note": "May compound drowsiness with sedative medications."},
  {"id": "rule_valerian_pregnancy", "herb_id": "valerian", "condition": "pregnancy", "severity": "high", "note": "Insufficient safety data in pregnancy."},
  {"id": "rule_valerian_pediatric", "herb_id": "valerian", "condition": "pediatric", "severity": "high", "note": "Not established as safe for children."},
  {"id": "rule_peppermint_gerd", "herb_id": "peppermint", "condition": "gerd", "severity": "moderate", "note": "May relax the lower esophageal sphincter and worsen reflux."},
  {"id": "rule_milk_thistle_hormone", "herb_id": "milk_thistle", "condition": "hormone_sensitive_condition", "severity": "moderate", "note": "Possible mild estrogenic activity; use caution with hormone-sensitive conditions."},
  {"id": "rule_elderberry_autoimmune", "herb_id": "elderberry", "condition": "autoimmune_condition", "severity": "moderate", "note": "Immune-stimulating effect may not be appropriate for autoimmune conditions."},
  {"id": "rule_echinacea_autoimmune", "herb_id": "echinacea", "condition": "autoimmune_condition", "severity": "moderate", "note": "Immune-stimulating effect may not be appropriate for autoimmune conditions."},
  {"id": "rule_ginkgo_anticoag", "herb_id": "ginkgo", "condition": "anticoagulant_medication", "severity": "high", "note": "Notable bleeding-risk interaction with blood thinners."},
  {"id": "rule_holy_basil_anticoag", "herb_id": "holy_basil", "condition": "anticoagulant_medication", "severity": "moderate", "note": "May have mild antiplatelet activity."},
  {"id": "rule_holy_basil_pregnancy", "herb_id": "holy_basil", "condition": "pregnancy", "severity": "moderate", "note": "Traditionally avoided in pregnancy at medicinal doses."},
  {"id": "rule_licorice_hypertension", "herb_id": "licorice_root", "condition": "hypertension", "severity": "high", "note": "Can raise blood pressure and cause potassium loss with regular use."},
  {"id": "rule_licorice_pregnancy", "herb_id": "licorice_root", "condition": "pregnancy", "severity": "moderate", "note": "High intake linked to concerns in pregnancy."},
  {"id": "rule_licorice_pediatric", "herb_id": "licorice_root", "condition": "pediatric", "severity": "high", "note": "Not established as safe for children at medicinal doses."},
  {"id": "rule_nettle_anticoag", "herb_id": "nettle", "condition": "anticoagulant_medication", "severity": "moderate", "note": "May have mild effects on blood clotting."},
  {"id": "rule_dandelion_kidney", "herb_id": "dandelion", "condition": "kidney_disease", "severity": "moderate", "note": "Diuretic effect warrants caution with kidney impairment."},
  {"id": "rule_hawthorn_cardiac", "herb_id": "hawthorn", "condition": "cardiac_medication", "severity": "high", "note": "Can interact with heart medications; requires clinician oversight."},
  {"id": "rule_maca_hormone", "herb_id": "maca", "condition": "hormone_sensitive_condition", "severity": "moderate", "note": "Possible hormonal activity; use caution with hormone-sensitive conditions."},
  {"id": "rule_rhodiola_bipolar", "herb_id": "rhodiola", "condition": "bipolar_disorder", "severity": "moderate", "note": "Stimulating adaptogen effect may not suit bipolar disorder; clinician input advised."},
  {"id": "rule_passionflower_sedative", "herb_id": "passionflower", "condition": "sedative_medication", "severity": "moderate", "note": "May compound drowsiness with sedative medications."},
  {"id": "rule_feverfew_pregnancy", "herb_id": "feverfew", "condition": "pregnancy", "severity": "high", "note": "Traditionally associated with uterine stimulant activity; avoid in pregnancy."},
  {"id": "rule_feverfew_anticoag", "herb_id": "feverfew", "condition": "anticoagulant_medication", "severity": "moderate", "note": "May inhibit platelet aggregation; caution with blood thinners."},
  {"id": "rule_cramp_bark_pregnancy", "herb_id": "cramp_bark", "condition": "pregnancy", "severity": "moderate", "note": "Traditional use affecting uterine smooth muscle; avoid without clinician guidance in pregnancy."},
  {"id": "rule_chasteberry_pregnancy", "herb_id": "chasteberry", "condition": "pregnancy", "severity": "high", "note": "Hormonal activity means insufficient safety data in pregnancy."},
  {"id": "rule_chasteberry_hormone", "herb_id": "chasteberry", "condition": "hormone_sensitive_condition", "severity": "high", "note": "Affects prolactin and estrogen/progesterone balance; avoid with hormone-sensitive conditions or hormonal medication, including birth control."},
  {"id": "rule_boswellia_pregnancy", "herb_id": "boswellia", "condition": "pregnancy", "severity": "moderate", "note": "Insufficient safety data in pregnancy and breastfeeding."},
  {"id": "rule_brahmi_thyroid", "herb_id": "brahmi", "condition": "thyroid_disorder", "severity": "moderate", "note": "May influence thyroid hormone activity."},
  {"id": "rule_brahmi_pregnancy", "herb_id": "brahmi", "condition": "pregnancy", "severity": "moderate", "note": "Insufficient safety data in pregnancy and breastfeeding."},
  {"id": "rule_guduchi_autoimmune", "herb_id": "guduchi", "condition": "autoimmune_condition", "severity": "high", "note": "Documented case reports of drug-induced autoimmune-like hepatitis; immune-stimulating effect may not be appropriate for autoimmune conditions."},
  {"id": "rule_guduchi_liver", "herb_id": "guduchi", "condition": "liver_disease", "severity": "high", "note": "Documented case reports of liver injury following Guduchi/Giloy use, despite traditional hepatoprotective reputation."},
  {"id": "rule_neem_pregnancy", "herb_id": "neem", "condition": "pregnancy", "severity": "high", "note": "Documented abortifacient and teratogenic effects in animal studies; avoid during pregnancy and while attempting conception."},
  {"id": "rule_neem_pediatric", "herb_id": "neem", "condition": "pediatric", "severity": "high", "note": "Oral neem oil has been linked to reported deaths in children; not established as safe for children."},
  {"id": "rule_fenugreek_pregnancy", "herb_id": "fenugreek", "condition": "pregnancy", "severity": "moderate", "note": "Traditionally associated with uterine stimulant activity at medicinal doses."},
  {"id": "rule_gotu_kola_pregnancy", "herb_id": "gotu_kola", "condition": "pregnancy", "severity": "moderate", "note": "Herbs with stimulant/emmenagogue actions are traditionally avoided in pregnancy."},
  {"id": "rule_gotu_kola_liver", "herb_id": "gotu_kola", "condition": "liver_disease", "severity": "moderate", "note": "Rare cases of liver toxicity have been reported."},
  {"id": "rule_shatavari_hormone", "herb_id": "shatavari", "condition": "hormone_sensitive_condition", "severity": "moderate", "note": "Steroidal saponins have estrogen-receptor affinity; use caution with hormone-sensitive conditions."},
  {"id": "rule_guggul_thyroid", "herb_id": "guggul", "condition": "thyroid_disorder", "severity": "high", "note": "Stimulates thyroid hormone synthesis; contraindicated in hyperthyroidism."},
  {"id": "rule_guggul_pregnancy", "herb_id": "guggul", "condition": "pregnancy", "severity": "moderate", "note": "Traditionally avoided in pregnancy and breastfeeding."},
  {"id": "rule_guggul_anticoag", "herb_id": "guggul", "condition": "anticoagulant_medication", "severity": "moderate", "note": "May interact with blood thinners and CYP3A-metabolized drugs."},
  {"id": "rule_guggul_hormone", "herb_id": "guggul", "condition": "hormone_sensitive_condition", "severity": "moderate", "note": "May interact with oral contraceptives and hormone-sensitive conditions."},
  {"id": "rule_arjuna_anticoag", "herb_id": "arjuna", "condition": "anticoagulant_medication", "severity": "moderate", "note": "Exhibits antiplatelet and anticoagulant activity similar to aspirin; may potentiate blood thinners."},
  {"id": "rule_punarnava_kidney", "herb_id": "punarnava", "condition": "kidney_disease", "severity": "moderate", "note": "Diuretic effect and fluid-electrolyte shifts warrant caution with kidney impairment or kidney stones."},
  {"id": "rule_punarnava_pregnancy", "herb_id": "punarnava", "condition": "pregnancy", "severity": "moderate", "note": "Traditionally avoided beyond the first trimester due to potential uterine stimulation."},
  {"id": "rule_astragalus_autoimmune", "herb_id": "astragalus", "condition": "autoimmune_condition", "severity": "moderate", "note": "Immune-stimulating effect may not be appropriate for autoimmune conditions."},
  {"id": "rule_astragalus_pregnancy", "herb_id": "astragalus", "condition": "pregnancy", "severity": "moderate", "note": "Traditionally avoided in pregnancy and breastfeeding."},
  {"id": "rule_ginseng_hypertension", "herb_id": "panax_ginseng", "condition": "hypertension", "severity": "moderate", "note": "May raise blood pressure in some individuals."},
  {"id": "rule_ginseng_anticoag", "herb_id": "panax_ginseng", "condition": "anticoagulant_medication", "severity": "moderate", "note": "May decrease the effectiveness of warfarin and other anticoagulants."},
  {"id": "rule_schisandra_pregnancy", "herb_id": "schisandra", "condition": "pregnancy", "severity": "moderate", "note": "Insufficient safety data in pregnancy and breastfeeding."},
  {"id": "rule_reishi_anticoag", "herb_id": "reishi", "condition": "anticoagulant_medication", "severity": "moderate", "note": "May have antiplatelet activity; caution advised with anticoagulant or antiplatelet medication."},
  {"id": "rule_he_shou_wu_liver", "herb_id": "he_shou_wu", "condition": "liver_disease", "severity": "disallowed", "note": "Documented cases of severe, occasionally fatal liver injury; recurrence on rechallenge is common. Not appropriate for anyone with existing liver disease."},
  {"id": "rule_he_shou_wu_autoimmune", "herb_id": "he_shou_wu", "condition": "autoimmune_condition", "severity": "high", "note": "Liver injury appears to be immunologically mediated in genetically susceptible individuals; extra caution for anyone with autoimmune conditions."},
  {"id": "rule_dong_quai_pregnancy", "herb_id": "dong_quai", "condition": "pregnancy", "severity": "high", "note": "May stimulate uterine contractions and has been linked to miscarriage; avoid especially in the first trimester."},
  {"id": "rule_dong_quai_anticoag", "herb_id": "dong_quai", "condition": "anticoagulant_medication", "severity": "moderate", "note": "Anticoagulant properties may increase bleeding risk when combined with blood thinners."},
  {"id": "rule_dong_quai_hormone", "herb_id": "dong_quai", "condition": "hormone_sensitive_condition", "severity": "moderate", "note": "Estrogenic activity may not be appropriate for hormone-sensitive conditions."},
  {"id": "rule_goji_berry_anticoag", "herb_id": "goji_berry", "condition": "anticoagulant_medication", "severity": "moderate", "note": "Well-documented interaction with warfarin, increasing bleeding risk."},
  {"id": "rule_cordyceps_autoimmune", "herb_id": "cordyceps", "condition": "autoimmune_condition", "severity": "moderate", "note": "Immune-modulating effect may not be appropriate for autoimmune conditions."},
  {"id": "rule_cordyceps_pregnancy", "herb_id": "cordyceps", "condition": "pregnancy", "severity": "moderate", "note": "Insufficient safety data in pregnancy and breastfeeding."},
  {"id": "rule_bupleurum_liver", "herb_id": "bupleurum", "condition": "liver_disease", "severity": "high", "note": "One of the most frequently implicated herbs in TCM-related liver injury reports, particularly with prolonged or high-dose use."}
]
